[
  {
    "req_id": "710",
    "res_id": "77A",
    "ecu_name": "CAN Gateway"
  },
  {
    "req_id": "7E1",
    "res_id": "7E9",
    "ecu_name": "变速箱控制单元"
  },
  {
    "req_id": "713",
    "res_id": "77D",
    "ecu_name": "ABS控制单元"
  },
  {
    "req_id": "7E0",
    "res_id": "7E8",
    "ecu_name": "引擎控制单元"
  },
  {
    "req_id": "712",
    "res_id": "77C",
    "ecu_name": "Power steering"
  },
  {
    "req_id": "732",
    "res_id": "79C",
    "ecu_name": "Authorization system for access and starting the engine"
  },
  {
    "req_id": "74D",
    "res_id": "7B7",
    "ecu_name": "Front passenger seat"
  },
  {
    "req_id": "200",
    "res_id": "23F",
    "ecu_name": "Head unit controller (VW TP2.0)"
  },
  {
    "req_id": "746",
    "res_id": "7B0",
    "ecu_name": "Heater and climate"
  },
  {
    "req_id": "70E",
    "res_id": "778",
    "ecu_name": "Onboard supply control unit"
  },
  {
    "req_id": "200",
    "res_id": "224",
    "ecu_name": "Slide Door Left (VW TP2.0)"
  },
  {
    "req_id": "770",
    "res_id": "7DA",
    "ecu_name": "Media player 1"
  },
  {
    "req_id": "200",
    "res_id": "24F",
    "ecu_name": "Digital radio tuner (VW TP2.0)"
  },
  {
    "req_id": "70A",
    "res_id": "774",
    "ecu_name": "Parking Assistant 2"
  },
  {
    "req_id": "7E2",
    "res_id": "7EA",
    "ecu_name": "Engine Electronics No.2"
  },
  {
    "req_id": "757",
    "res_id": "7C1",
    "ecu_name": "Active cruise control"
  },
  {
    "req_id": "772",
    "res_id": "7DC",
    "ecu_name": "Electronic system Damping controls"
  },
  {
    "req_id": "715",
    "res_id": "77F",
    "ecu_name": "SRS"
  },
  {
    "req_id": "70C",
    "res_id": "776",
    "ecu_name": "Steering column"
  },
  {
    "req_id": "714",
    "res_id": "77E",
    "ecu_name": "Dashboard"
  },
  {
    "req_id": "76A",
    "res_id": "7D4",
    "ecu_name": "Additional heater"
  },
  {
    "req_id": "200",
    "res_id": "240",
    "ecu_name": "Car location(VW TP2.0)"
  },
  {
    "req_id": "716",
    "res_id": "780",
    "ecu_name": "Active steering"
  },
  {
    "req_id": "200",
    "res_id": "22B",
    "ecu_name": "Driver identification (VW TP2.0)"
  },
  {
    "req_id": "200",
    "res_id": "250",
    "ecu_name": "Mediaplayer 2(VW TP2.0)"
  },
  {
    "req_id": "200",
    "res_id": "25F",
    "ecu_name": "Satelight radio tuner (VW TP2.0)"
  },
  {
    "req_id": "730",
    "res_id": "79A",
    "ecu_name": "FLA"
  },
  {
    "req_id": "728",
    "res_id": "792",
    "ecu_name": "Energy Management 2"
  },
  {
    "req_id": "70F",
    "res_id": "779",
    "ecu_name": "Four-wheeldrive"
  },
  {
    "req_id": "73B",
    "res_id": "7A5",
    "ecu_name": "Increased braking force"
  },
  {
    "req_id": "711",
    "res_id": "77B",
    "ecu_name": "Immobilizer"
  },
  {
    "req_id": "72D",
    "res_id": "797",
    "ecu_name": "Electric folding roof"
  },
  {
    "req_id": "200",
    "res_id": "23E",
    "ecu_name": "Rear head unit controller (VW TP2.0)"
  },
  {
    "req_id": "71A",
    "res_id": "784",
    "ecu_name": "Climate Control Panel"
  },
  {
    "req_id": "200",
    "res_id": "238",
    "ecu_name": "Left side lights control (VW TP2.0)"
  },
  {
    "req_id": "200",
    "res_id": "259",
    "ecu_name": "Voice amplifier (VW TP2.0)"
  },
  {
    "req_id": "200",
    "res_id": "254",
    "ecu_name": "Mediaplayer 3(VW TP2.0)"
  },
  {
    "req_id": "200",
    "res_id": "24C",
    "ecu_name": "Digital TV-tuner (VW TP2.0)"
  },
  {
    "req_id": "71E",
    "res_id": "788",
    "ecu_name": "Differentiallock electronics"
  },
  {
    "req_id": "755",
    "res_id": "7BF",
    "ecu_name": "Ride height control system"
  },
  {
    "req_id": "74C",
    "res_id": "7B6",
    "ecu_name": "Driver seat adjustment"
  },
  {
    "req_id": "76C",
    "res_id": "7D6",
    "ecu_name": "Navigation system"
  },
  {
    "req_id": "200",
    "res_id": "239",
    "ecu_name": "Right side lights control(VW TP2.0)"
  },
  {
    "req_id": "74E",
    "res_id": "7B8",
    "ecu_name": "Lane change assistant"
  },
  {
    "req_id": "72C",
    "res_id": "796",
    "ecu_name": "Special function"
  },
  {
    "req_id": "200",
    "res_id": "262",
    "ecu_name": "Mediaplayer 4(VW TP2.0)"
  },
  {
    "req_id": "74A",
    "res_id": "7B4",
    "ecu_name": "Driver door electronic equipment"
  },
  {
    "req_id": "712",
    "res_id": "77C",
    "ecu_name": "Power steering"
  },
  {
    "req_id": "200",
    "res_id": "221",
    "ecu_name": "Central comfort systems module (VW TP2.0)"
  },
  {
    "req_id": "76F",
    "res_id": "7D9",
    "ecu_name": "Acoustic system"
  },
  {
    "req_id": "200",
    "res_id": "237",
    "ecu_name": "Rear seat behind driver (VW TP2.0)"
  },
  {
    "req_id": "200",
    "res_id": "25D",
    "ecu_name": "Rear right control and indication unit (VW TP2.0)"
  },
  {
    "req_id": "200",
    "res_id": "208",
    "ecu_name": "TPMS #2(VW TP2.0)"
  },
  {
    "req_id": "200",
    "res_id": "228",
    "ecu_name": "Body control unit #2 (VW TP2.0)"
  },
  {
    "req_id": "74B",
    "res_id": "B5",
    "ecu_name": "Front passenger door electronics"
  },
  {
    "req_id": "752",
    "res_id": "BC",
    "ecu_name": "Parking brake"
  },
  {
    "req_id": "754",
    "res_id": "BE",
    "ecu_name": "Headlights corrector"
  },
  {
    "req_id": "200",
    "res_id": "252",
    "ecu_name": "Head unit(MMI)(VW TP2.0)"
  },
  {
    "req_id": "76D",
    "res_id": "D7",
    "ecu_name": "Tv tuner"
  },
  {
    "req_id": "200",
    "res_id": "241",
    "ecu_name": "Tow protection (VW TP2.0)"
  },
  {
    "req_id": "200",
    "res_id": "21A",
    "ecu_name": "Lane assist(VW TP2.0)"
  },
  {
    "req_id": "200",
    "res_id": "24B",
    "ecu_name": "Control(VW TP2.0)"
  },
  {
    "req_id": "200",
    "res_id": "25E",
    "ecu_name": "Rear left control and indication unit (VW TP2.0)"
  },
  {
    "req_id": "773",
    "res_id": "7DD",
    "ecu_name": "Electronic Information System 1"
  },
  {
    "req_id": "200",
    "res_id": "233",
    "ecu_name": "Battery Regulation using CAN (VW TP2.0)"
  },
  {
    "req_id": "200",
    "res_id": "246",
    "ecu_name": "Easy entry driver side (VW TP2.0)"
  },
  {
    "req_id": "200",
    "res_id": "224",
    "ecu_name": "Rear left door electoronics (VW TP2.0)"
  },
  {
    "req_id": "70B",
    "res_id": "75",
    "ecu_name": "TPMS"
  },
  {
    "req_id": "200",
    "res_id": "236",
    "ecu_name": "Rear seats adjustment (VW TP2.0)"
  },
  {
    "req_id": "200",
    "res_id": "25C",
    "ecu_name": "Voice control(VW TP2.0)"
  },
  {
    "req_id": "200",
    "res_id": "232",
    "ecu_name": "Wipers electronics(VW TP2.0)"
  },
  {
    "req_id": "747",
    "res_id": "7B1",
    "ecu_name": "Trailer functions"
  },
  {
    "req_id": "769",
    "res_id": "7D3",
    "ecu_name": "Rear view camera system var.1"
  },
  {
    "req_id": "200",
    "res_id": "23D",
    "ecu_name": "Control Head Roof(VW TP2.0)"
  },
  {
    "req_id": "723",
    "res_id": "78D",
    "ecu_name": "Tailgate/Boot lid"
  },
  {
    "req_id": "745",
    "res_id": "7AF",
    "ecu_name": "Comfort system central module 2"
  },
  {
    "req_id": "71D",
    "res_id": "787",
    "ecu_name": "Charger"
  },
  {
    "req_id": "200",
    "res_id": "225",
    "ecu_name": "Rear right door electronics (VW TP2.0)"
  },
  {
    "req_id": "200",
    "res_id": "247",
    "ecu_name": "Easy entry passenger side (VW TP2.0)"
  },
  {
    "req_id": "200",
    "res_id": "21B",
    "ecu_name": "Chassis Control(VW TP2.0)"
  },
  {
    "req_id": "767",
    "res_id": "7D1",
    "ecu_name": "Emergency Call and Communication Module"
  },
  {
    "req_id": "70A",
    "res_id": "774",
    "ecu_name": "Parking assistant"
  },
  {
    "req_id": "200",
    "res_id": "225",
    "ecu_name": "Slide Door Right (VW TP2.0)"
  },
  {
    "req_id": "200",
    "res_id": "22E",
    "ecu_name": "Additional heater (VW TP2.0)"
  },
  {
    "req_id": "200",
    "res_id": "248",
    "ecu_name": "Indication panelin the dashboard (VW TP2.0)"
  },
  {
    "req_id": "75A",
    "res_id": "7C4",
    "ecu_name": "Electronic Information System 2"
  },
  {
    "req_id": "7E5",
    "res_id": "7ED",
    "ecu_name": "Hybrid battery management (UDS)"
  },
  {
    "req_id": "6BC",
    "res_id": "726",
    "ecu_name": "SRS/Airbag(UDS)"
  },
  {
    "req_id": "784",
    "res_id": "7EE",
    "ecu_name": "ESP(UDS)"
  },
  {
    "req_id": "74F",
    "res_id": "7B9",
    "ecu_name": "Front Assistant A5(UDS)"
  },
  {
    "req_id": "762",
    "res_id": "7CC",
    "ecu_name": "Sensors for brake control unit (UDS"
  },
  {
    "req_id": "73E",
    "res_id": "7A8",
    "ecu_name": "Rear door behind driver (UDS)"
  },
  {
    "req_id": "73F",
    "res_id": "7A9",
    "ecu_name": "Rear door behind passenger (UDS)"
  },
  {
    "req_id": "765",
    "res_id": "7CF",
    "ecu_name": "High-voltage battery charging management(UDS)"
  },
  {
    "req_id": "744",
    "res_id": "7AE",
    "ecu_name": "High-voltage battery charger (UDS)"
  },

  {
    "req_id": "17FC0076",
    "res_id": "17FE0076",
    "ecu_name": "Engine(EVO/29bit)"
  },
  {
    "req_id": "17FC0077",
    "res_id": "17FE0077",
    "ecu_name": "Gearbox(EVO/29bit)"
  },
  {
    "req_id": "17FC008B",
    "res_id": "17FE008B",
    "ecu_name": "Comfort unit"
  },
  {
    "req_id": "17FC00A9",
    "res_id": "17FE00A9",
    "ecu_name": "Multi-functionalunit"
  },
  {
    "req_id": "17FC007C",
    "res_id": "17FE007C",
    "ecu_name": "Electro-engine"
  },
  {
    "req_id": "17FC007B",
    "res_id": "17FE007B",
    "ecu_name": "Battery management system"
  },
  {
    "req_id": "17FC0096",
    "res_id": "17FE0096",
    "ecu_name": "Headlight control left 2"
  },
  {
    "req_id": "17FC0097",
    "res_id": "17FE0097",
    "ecu_name": "Headlight control right 2"
  },
  {
    "req_id": "17FC00A0",
    "res_id": "17FE00A0",
    "ecu_name": "Roof control #2"
  },
  {
    "req_id": "17FC160A",
    "res_id": "17FE160A",
    "ecu_name": "Left LED headlight control 1"
  },
  {
    "req_id": "17FC160B",
    "res_id": "17FE160B",
    "ecu_name": "Right LED headlight control 1"
  },
  {
    "req_id": "17FC16D1",
    "res_id": "17FE16D1",
    "ecu_name": "Battery cell control module 1"
  },
  {
    "req_id": "17FC16D2",
    "res_id": "17FE16D2",
    "ecu_name": "Battery cell control module 2"
  },
  {
    "req_id": "17FC16D3",
    "res_id": "17FE16D3",
    "ecu_name": "Battery cell control module 3"
  },
  {
    "req_id": "17FC16D4",
    "res_id": "17FE16D4",
    "ecu_name": "Battery cell control module 4"
  },
  {
    "req_id": "17FC16D5",
    "res_id": "17FE16D5",
    "ecu_name": "Battery cell control module 5"
  },
  {
    "req_id": "17FC16D6",
    "res_id": "17FE16D6",
    "ecu_name": "Battery cell control module 6"
  },
  {
    "req_id": "17FC16D7",
    "res_id": "17FE16D7",
    "ecu_name": "Battery cell control module 7"
  },
  {
    "req_id": "17FC16D8",
    "res_id": "17FE16D8",
    "ecu_name": "Battery cell control module 8"
  },
  {
    "req_id": "17FC007B",
    "res_id": "17FE007B",
    "ecu_name": "HV BMS"
  },
  {
    "req_id": "17FC00B9",
    "res_id": "17FE00B9",
    "ecu_name": "DC Charde"
  }
]